Metadata-Version: 1.0
Name: pyjrdatahost
Version: 0.1
Summary: python data server.
Home-page: https://gitee.com/hzy15610046011/python_data_host
Author: Zhanyi Hou
Author-email: 3120388018@qq.com
License: MuLan2.0
Platform: UNKNOWN
